stocklib/Exceptions.py
stocklib/__init__.py
stocklib-2.1.1.dist-info/METADATA
stocklib-2.1.1.dist-info/WHEEL
stocklib-2.1.1.dist-info/top_level.txt
stocklib-2.1.1.dist-info/RECORD
