Metadata-Version: 2.1
Name: stocklib
Version: 2.1.1
Summary: Get real-time stock data!
Home-page: https://github.com/SammmE/StockLib
Author: SammmE
License: MIT
Classifier: License :: OSI Approved :: MIT License
Classifier: Programming Language :: Python :: 3
Classifier: Programming Language :: Python :: 3.10
Requires-Dist: beautifulsoup4
Requires-Dist: requests
